odoo8_addon_account_credit_control-8.0.0.3.0.99.dev71-py3.8-nspkg.pth
odoo_addons/account_credit_control/README.rst
odoo_addons/account_credit_control/__init__.py
odoo_addons/account_credit_control/__openerp__.py
odoo_addons/account_credit_control/account.py
odoo_addons/account_credit_control/account_view.xml
odoo_addons/account_credit_control/company.py
odoo_addons/account_credit_control/company_view.xml
odoo_addons/account_credit_control/credit_control_demo.xml
odoo_addons/account_credit_control/data.xml
odoo_addons/account_credit_control/invoice.py
odoo_addons/account_credit_control/line.py
odoo_addons/account_credit_control/line_view.xml
odoo_addons/account_credit_control/mail.py
odoo_addons/account_credit_control/partner.py
odoo_addons/account_credit_control/partner_view.xml
odoo_addons/account_credit_control/policy.py
odoo_addons/account_credit_control/policy_view.xml
odoo_addons/account_credit_control/run.py
odoo_addons/account_credit_control/run_view.xml
odoo_addons/account_credit_control/i18n/ab.po
odoo_addons/account_credit_control/i18n/account_credit_control.pot
odoo_addons/account_credit_control/i18n/am.po
odoo_addons/account_credit_control/i18n/ar.po
odoo_addons/account_credit_control/i18n/bg.po
odoo_addons/account_credit_control/i18n/bs.po
odoo_addons/account_credit_control/i18n/ca.po
odoo_addons/account_credit_control/i18n/ca_ES.po
odoo_addons/account_credit_control/i18n/cs.po
odoo_addons/account_credit_control/i18n/da.po
odoo_addons/account_credit_control/i18n/da_DK.po
odoo_addons/account_credit_control/i18n/de.po
odoo_addons/account_credit_control/i18n/el_GR.po
odoo_addons/account_credit_control/i18n/en_AU.po
odoo_addons/account_credit_control/i18n/en_GB.po
odoo_addons/account_credit_control/i18n/es.po
odoo_addons/account_credit_control/i18n/es_AR.po
odoo_addons/account_credit_control/i18n/es_BO.po
odoo_addons/account_credit_control/i18n/es_CL.po
odoo_addons/account_credit_control/i18n/es_CO.po
odoo_addons/account_credit_control/i18n/es_CR.po
odoo8_addon_account_credit_control-8.0.0.3.0.99.dev71.dist-info/METADATA
odoo8_addon_account_credit_control-8.0.0.3.0.99.dev71.dist-info/WHEEL
odoo8_addon_account_credit_control-8.0.0.3.0.99.dev71.dist-info/namespace_packages.txt
odoo8_addon_account_credit_control-8.0.0.3.0.99.dev71.dist-info/top_level.txt
odoo8_addon_account_credit_control-8.0.0.3.0.99.dev71.dist-info/RECORD
